Metadata-Version: 2.4
Name: llama-index-readers-docugami
Version: 0.4.1
Summary: llama-index readers docugami integration
Author-email: Your Name <you@example.com>
Maintainer: tjaffri
License-Expression: MIT
License-File: LICENSE
Keywords: doc,docugami,docx,pdf,xml
Requires-Python: <4.0,>=3.9
Requires-Dist: dgml-utils<0.4,>=0.3.1
Requires-Dist: llama-index-core<0.15,>=0.13.0
Requires-Dist: lxml~=4.9.3
